.svnignore
README.txt
setup.cfg
setup.py
collective/__init__.py
collective.contentrules.linguatarget.egg-info/PKG-INFO
collective.contentrules.linguatarget.egg-info/SOURCES.txt
collective.contentrules.linguatarget.egg-info/dependency_links.txt
collective.contentrules.linguatarget.egg-info/entry_points.txt
collective.contentrules.linguatarget.egg-info/namespace_packages.txt
collective.contentrules.linguatarget.egg-info/not-zip-safe
collective.contentrules.linguatarget.egg-info/requires.txt
collective.contentrules.linguatarget.egg-info/top_level.txt
collective/contentrules/__init__.py
collective/contentrules/linguatarget/__init__.py
collective/contentrules/linguatarget/actions.py
collective/contentrules/linguatarget/configure.zcml
collective/contentrules/linguatarget/profiles/default/metadata.xml
collective/contentrules/linguatarget/tests/__init__.py
collective/contentrules/linguatarget/tests/test_linguacopy.py
collective/contentrules/linguatarget/tests/test_linguamove.py
docs/HISTORY.txt