Metadata-Version: 1.0
Name: collective.contentrules.linguatarget
Version: 0.5
Summary: This package adds a custom content rule that takes the target folder's translations into account
Home-page: http://plone.org/products/collective.contentrules.linguatarget
Author: JC Brand, Syslab.com GmbH
Author-email: brand@syslab.com
License: GPL
Keywords: syslab linguaplone linguatarget plone contentrules
Platform: UNKNOWN
Classifier: Programming Language :: Python
Classifier: Topic :: Software Development :: Libraries :: Python Modules
